examples/__init__.py
terminhtml_recorder/__init__.py
terminhtml_recorder/__main__.py
terminhtml_recorder/cli.py
terminhtml_recorder/converter.py
terminhtml_recorder/exc.py
terminhtml_recorder/formats.py
terminhtml_recorder/logger.py
terminhtml_recorder/recorder.py
terminhtml_recorder/temp_path.py
terminhtml_recorder/video.py
tests/__init__.py
tests/config.py
tests/ext_click.py
tests/generate.py
tests/test_cli.py
tests/test_recorder.py
tests/checks/__init__.py
tests/checks/gif.py
tests/fixtures/__init__.py
tests/fixtures/temp_folder.py
terminhtml_recorder-1.0.0a4.dist-info/LICENSE.md
terminhtml_recorder-1.0.0a4.dist-info/METADATA
terminhtml_recorder-1.0.0a4.dist-info/WHEEL
terminhtml_recorder-1.0.0a4.dist-info/entry_points.txt
terminhtml_recorder-1.0.0a4.dist-info/top_level.txt
terminhtml_recorder-1.0.0a4.dist-info/RECORD
