Metadata-Version: 2.1
Name: terminhtml-recorder
Version: 1.0.0a4
Summary: Create video and image files via TerminHTML rather than HTML/CSS/JS
Home-page: https://github.com/nickderobertis/terminhtml-recorder
Author: Nick DeRobertis
Author-email: derobertis.nick@gmail.com
License: MIT
Project-URL: Code, https://github.com/nickderobertis/terminhtml-recorder
Project-URL: Documentation, https://nickderobertis.github.io/terminhtml-recorder
Classifier: Development Status :: 3 - Alpha
Classifier: Intended Audience :: Developers
Classifier: Programming Language :: Python :: 3.6
Classifier: Programming Language :: Python :: 3.7
License-File: LICENSE.md
Requires-Dist: moviepy
Requires-Dist: playwright
Requires-Dist: rich
Requires-Dist: terminhtml
Requires-Dist: cliconf
